{
  "type": "FeatureCollection",
  "features": [
    {
      "type": "Feature",
      "id": "PC_1",
      "properties": {
        "key": "PC",
        "city": "Port Coquitlam",
        "type": "Problem",
        "location": "From Port Coquitlam to New West",
        "description": "Connection between Port Coquitlam and New Westminster really requires improvement.",
        "date":"2021-09-04"
      },
      "geometry": {
        "type": "Point",
        "coordinates": [
          -122.748646,
          49.246313
        ]
      }
    },
    {
      "type": "Feature",
      "id": "PC_2",
      "properties": {
        "key": "PC",
        "city": "Port Coquitlam",
        "type": "Problem",
        "location": "East to West along Kingsway",
        "description": "My concern is the east west route along Kingsway. Ample room for a new bike path in the Hydro ROW.",
        "date":"2021-09-03"
      },
      "geometry": {
        "type": "Point",
        "coordinates": [
          -122.749503,
          49.247329
        ]
      }
    },
    {
      "type": "Feature",
      "id": "PC_3",
      "properties": {
        "key": "PC",
        "city": "Port Coquitlam",
        "type": "Problem",
        "location": "Gates Park",
        "description": "It should be monitory that all bicycles adult or child should have some sort of bell on the front of the bicycle to let people know that someone is coming up from the back.",
        "date":"2021-11-30"
      },
      "geometry": {
        "type": "Point",
        "coordinates": [
          -122.791421,
          49.259188
        ]
      }
    },
    {
      "type": "Feature",
      "id": "PC_4",
      "properties": {
        "key": "PC",
        "city": "Port Coquitlam",
        "type": "Problem",
        "location": "Lions Park",
        "description": "It should be monitory that all bicycles adult or child should have some sort of bell on the front of the bicycle to let people know that someone is coming up from the back.",
        "date":"2021-11-30"
      },
      "geometry": {
        "type": "Point",
        "coordinates": [
          -122.779912,
          49.266960
        ]
      }
    }
  ]
}